pyarmips.cp313-win_amd64.pyd
pyarmips-0.11.3.dist-info/LICENSE
pyarmips-0.11.3.dist-info/METADATA
pyarmips-0.11.3.dist-info/WHEEL
pyarmips-0.11.3.dist-info/top_level.txt
pyarmips-0.11.3.dist-info/RECORD
