Metadata-Version: 2.1
Name: pyarmips
Version: 0.11.3
Summary: Python interface for armips.
Home-page: https://github.com/Illidanz/pyarmips
Author: Illidan
License: UNKNOWN
Platform: UNKNOWN
Classifier: Programming Language :: Python :: 3
Classifier: License :: OSI Approved :: MIT License
License-File: LICENSE
